drysponge/__init__.py
drysponge/aead.py
drysponge/drygascon.py
drysponge/drygascon128_aead.py
drysponge/drygascon128_hash.py
drysponge/drygascon256_aead.py
drysponge/drygascon256_hash.py
drysponge/gascon.py
drysponge/hash.py
drysponge/base/__init__.py
drysponge-1.0.10.dist-info/METADATA
drysponge-1.0.10.dist-info/WHEEL
drysponge-1.0.10.dist-info/top_level.txt
drysponge-1.0.10.dist-info/RECORD
