Metadata-Version: 2.1
Name: drysponge
Version: 1.0.10
Summary: DryGASCON reference implementation
Home-page: https://github.com/sebastien-riou/DryGASCON
Author: Sebastien Riou
Author-email: matic@nimp.co.uk
License: UNKNOWN
Platform: UNKNOWN
Classifier: Programming Language :: Python :: 3
Classifier: License :: OSI Approved :: Apache Software License
Classifier: Operating System :: OS Independent
Classifier: Development Status :: 5 - Production/Stable
Requires-Python: >=3.5
